{
    "measurement_node": "china",
    "peer_cloud_server": "aws korea",
    "data_flow_direction": "upload",
    "link_type": "cellular",
    "data_source_url": "https://pantheon.stanford.edu/result/146/",
    "config": {
        "uplink": {
            "bottleneck_bandwidth": 2460,
            "buffer_size_bytes": 86182,
            "buffer_size_packets": 57,
            "propagation_delay": 192,
            "cross_traffic_pattern": [0, 1043, 387, 149, 70, 240, 19, 330, 225, 121, 29, 73, 165, 124, 274, 235, 160, 226, 290, 270, 110, 344, 195, 337, 228, 146, 282, 407, 67, 211]
        },
        "downlink": {
            "bottleneck_bandwidth": 10000,
            "buffer_size_bytes": 15000000,
            "buffer_size_packets": 10000,
            "propagation_delay": 0,
            "cross_traffic_pattern": []
        },
        "__comment": "bottleneck_bandwidth is in kbps, buffer_size_packets is in number of MTU sized packets, propagation_delay is in ms, and the cross_traffic_pattern is a 30s long timeseries with each entry in kbps"
    }
}