{
    "measurement_node": "colombia",
    "peer_cloud_server": "aws brazil",
    "data_flow_direction": "upload",
    "link_type": "cellular",
    "data_source_url": "https://pantheon.stanford.edu/result/547/",
    "config": {
        "uplink": {
            "bottleneck_bandwidth": 660,
            "buffer_size_bytes": 594042,
            "buffer_size_packets": 396,
            "propagation_delay": 679,
            "cross_traffic_pattern": [0, 5020, 589, 150, 87, 59, 57, 85, 83, 157, 127, 173, 165, 143, 140, 140, 140, 140, 140, 140, 140, 140, 140, 140, 140, 140, 140, 140, 140, 140]
        },
        "downlink": {
            "bottleneck_bandwidth": 10000,
            "buffer_size_bytes": 15000000,
            "buffer_size_packets": 10000,
            "propagation_delay": 0,
            "cross_traffic_pattern": []
        },
        "__comment": "bottleneck_bandwidth is in kbps, buffer_size_packets is in number of MTU sized packets, propagation_delay is in ms, and the cross_traffic_pattern is a 30s long timeseries with each entry in kbps"
    }
}